ppct-0.0.1.dist-info/METADATA
ppct-0.0.1.dist-info/WHEEL
ppct/__init__.py
ppct/design_patterns.py
ppct/line_reader.py
ppct/parallel.py
ppct/utlis.py
ppct-0.0.1.dist-info/RECORD
