Metadata-Version: 2.1
Name: ppct
Version: 0.0.1
Summary: Pure Python common toolset
Author: xfoobar
License: MIT
Requires-Python: >=3.11
